example/__init__.py
example/model.py
experiments_addon/__init__.py
experiments_addon/delete.py
experiments_addon/logger.py
tests/__init__.py
tests/test_delete.py
tests/test_logger.py
tests/test_model.py
sagemaker_experiments_logger-1.0.0.dist-info/LICENSE
sagemaker_experiments_logger-1.0.0.dist-info/METADATA
sagemaker_experiments_logger-1.0.0.dist-info/WHEEL
sagemaker_experiments_logger-1.0.0.dist-info/top_level.txt
sagemaker_experiments_logger-1.0.0.dist-info/RECORD
