Metadata-Version: 2.1
Name: sagemaker-experiments-logger
Version: 1.0.0
Summary: PyTorch Lightning Experiment Logger
Home-page: https://tsenst.github.io/lightning-experiments-logger/
Author: Tobias Senst
Author-email: tobias.senst@googlemail.com
License: Apache 2.0
Keywords: pytorch-lightning,AWS SageMaker,machine learning
Classifier: Programming Language :: Python :: 3
Classifier: Intended Audience :: Developers
Classifier: Intended Audience :: Education
Classifier: Intended Audience :: Science/Research
Classifier: Operating System :: OS Independent
Classifier: Topic :: Scientific/Engineering
Classifier: Topic :: Scientific/Engineering :: Mathematics
Classifier: Topic :: Scientific/Engineering :: Artificial Intelligence
Classifier: Topic :: Software Development
Classifier: Topic :: Software Development :: Libraries
Classifier: Topic :: Software Development :: Libraries :: Python Modules
Requires-Python: >=3.9
License-File: LICENSE
Requires-Dist: setuptools >=67.4.0
Requires-Dist: scikit-learn >=1.3.1
Requires-Dist: pytorch-lightning >=2.0.0
Requires-Dist: sagemaker >=2.190.0
Requires-Dist: torchvision >=0.16.0
Requires-Dist: torchmetrics >=0.11.4
Provides-Extra: dev
Requires-Dist: black ; extra == 'dev'
Requires-Dist: flake8 ; extra == 'dev'
Requires-Dist: isort ; extra == 'dev'
Requires-Dist: mypy ; extra == 'dev'
Requires-Dist: pylint ; extra == 'dev'
Requires-Dist: types-PyYAML ; extra == 'dev'
Provides-Extra: tests
Requires-Dist: moto ==4.2.5 ; extra == 'tests'
Requires-Dist: pytest ; extra == 'tests'
Requires-Dist: pytest-mock ; extra == 'tests'
Requires-Dist: pytest-cov ; extra == 'tests'
